{
    "tag": "m-panel",
    "name": "m-panel-meta:name",
    "production": true,
    "attributes": {
        "skin": {
            "type": "string",
            "values": [
                "light",
                "dark",
                "darker"
            ],
            "default": 0
        },
        "highlighted": {
            "type": "boolean",
            "default": false
        },
        "shadow": {
            "type": "boolean",
            "default": true
        },
        "border": {
            "type": "boolean",
            "default": false
        },
        "borderLarge": {
            "type": "boolean",
            "default": false
        },
        "padding": {
            "type": "boolean",
            "default": true
        },
        "paddingLarge": {
            "type": "boolean",
            "default": false
        },
        "paddingHeader": {
            "type": "boolean",
            "default": true
        },
        "paddingBody": {
            "type": "boolean",
            "default": true
        },
        "paddingFooter": {
            "type": "boolean",
            "default": true
        }
    },
    "overview": "panel.overview",
    "preview": "panel.preview"
}
