{
  "m-icon-file": {
    "prefix": "File Type: ",
    "image": "Image",
    "txt": "Text",
    "doc": "Word Document",
    "vsd": "Visio Diagram",
    "ppt": "Powerpoint Presentation",
    "xls": "Excel Spreadsheet",
    "accdb": "Access Database",
    "pdf": "PDF Document",
    "rm": "RealMedia Audio",
    "mov": "Quicktime Video",
    "wma": "Windows Media Video",
    "swf": "Flash",
    "video": "Mpeg Video",
    "music": "Audio",
    "zip": "Archive",
    "openoffice1": "Open Office Document",
    "odt": "Open Document Doc",
    "odp": "Open Document Presentation",
    "odg": "Open Document Drawing",
    "ods": "Open Document Spreadsheet",
    "odf": "Mathematical Formula Open Document",
    "odb": "Open Document Database",
    "spss": "SPSS Statistics",
    "dwg": "AutoCAD Drawing",
    "enl": "EndNote Bibliography",
    "sas": "SAS Dtatistics",
    "xml": "XML Data Format",
    "html": "HTML",
    "css": "Cascading Style Sheet",
    "json": "JSON Data Format",
    "js": "Code",
    "default": "Unrecognized File"
  }
}